axonode_chunker/__init__.py
axonode_chunker/chunker.py
axonode_chunker-0.2.0.dist-info/licenses/LICENSE
axonode_chunker-0.2.0.dist-info/METADATA
axonode_chunker-0.2.0.dist-info/WHEEL
axonode_chunker-0.2.0.dist-info/top_level.txt
axonode_chunker-0.2.0.dist-info/RECORD
