Metadata-Version: 2.4
Name: axonode-chunker
Version: 0.2.0
Summary: A semantic text chunking package for intelligent document processing
Author-email: Erez Azaria <erezazaria@users.noreply.github.com>
License: MIT
Project-URL: Homepage, https://github.com/bazilicum/axonode-chunker
Project-URL: Repository, https://github.com/bazilicum/axonode-chunker
Project-URL: Issues, https://github.com/bazilicum/axonode-chunker/issues
Project-URL: Author, https://www.linkedin.com/in/erez-azaria/
Classifier: Development Status :: 3 - Alpha
Classifier: Intended Audience :: Developers
Classifier: License :: OSI Approved :: MIT License
Classifier: Programming Language :: Python :: 3
Classifier: Programming Language :: Python :: 3.8
Classifier: Programming Language :: Python :: 3.9
Classifier: Programming Language :: Python :: 3.10
Classifier: Programming Language :: Python :: 3.11
Classifier: Programming Language :: Python :: 3.12
Classifier: Topic :: Text Processing :: Linguistic
Classifier: Topic :: Scientific/Engineering :: Artificial Intelligence
Requires-Python: >=3.8
License-File: LICENSE
Requires-Dist: numpy>=1.21.0
Requires-Dist: nltk>=3.8
Requires-Dist: scikit-learn>=1.0.0
Requires-Dist: langchain-core>=0.1.0
Provides-Extra: dev
Requires-Dist: pytest>=7.0.0; extra == "dev"
Requires-Dist: pytest-asyncio>=0.21.0; extra == "dev"
Requires-Dist: black>=22.0.0; extra == "dev"
Requires-Dist: flake8>=5.0.0; extra == "dev"
Requires-Dist: mypy>=1.0.0; extra == "dev"
Provides-Extra: examples
Requires-Dist: tiktoken>=0.1.0; extra == "examples"
Requires-Dist: sentence-transformers>=2.0.0; extra == "examples"
Provides-Extra: all
Requires-Dist: pytest>=7.0.0; extra == "all"
Requires-Dist: pytest-asyncio>=0.21.0; extra == "all"
Requires-Dist: black>=22.0.0; extra == "all"
Requires-Dist: flake8>=5.0.0; extra == "all"
Requires-Dist: mypy>=1.0.0; extra == "all"
Requires-Dist: tiktoken>=0.1.0; extra == "all"
Requires-Dist: sentence-transformers>=2.0.0; extra == "all"
Dynamic: license-file
